visen/__init__.py
visen/__main__.py
visen/format.py
visen-0.0.1.dist-info/METADATA
visen-0.0.1.dist-info/WHEEL
visen-0.0.1.dist-info/entry_points.txt
visen-0.0.1.dist-info/top_level.txt
visen-0.0.1.dist-info/RECORD
