Metadata-Version: 2.1
Name: visen
Version: 0.0.1
Summary: Format Vietnamese string tone
Home-page: https://github.com/nguyenvulebinh/visen
Author: Binh Nguyen
Author-email: nguyenvulebinh@gmail.com
License: MIT
Platform: UNKNOWN
Classifier: License :: OSI Approved :: MIT License
Classifier: Programming Language :: Python :: 3
Classifier: Programming Language :: Python :: 3.7
Requires-Dist: ftfy (==5.5.1)
Requires-Dist: bogo (==1.1)
